bh/__init__.py
bh-0.0.9.dist-info/licenses/LICENSE
bh-0.0.9.dist-info/METADATA
bh-0.0.9.dist-info/WHEEL
bh-0.0.9.dist-info/top_level.txt
bh-0.0.9.dist-info/RECORD
