Metadata-Version: 2.4
Name: bh
Version: 0.0.9
Summary: Fuzzy Linear Discriminant Analysis
Home-page: https://github.com/lyricalgrin/bh
License: apache-2.0
Platform: any
License-File: LICENSE
Requires-Dist: scikit-learn
Dynamic: license-file
